network_broadcast_api/README.md
network_broadcast_api/__init__.py
network_broadcast_api/network_broadcast_api_client.py
network_broadcast_api/network_broadcast_api_description.py
network_broadcast_api/py.typed
hiveio_network_broadcast_api-1.28.4.dist-info/METADATA
hiveio_network_broadcast_api-1.28.4.dist-info/WHEEL
hiveio_network_broadcast_api-1.28.4.dist-info/RECORD
